lcr_session/__init__.py
lcr_session/py.typed
lcr_session/session.py
lcr_session/urls.py
lcr_session/utils.py
lcr_session-1.2.0.dist-info/LICENSE
lcr_session-1.2.0.dist-info/METADATA
lcr_session-1.2.0.dist-info/WHEEL
lcr_session-1.2.0.dist-info/RECORD
