Metadata-Version: 2.3
Name: lcr_session
Version: 1.2.0
Summary: Session authentication to the Church of Jesus Christ of Latter Day Saints LCR System
License: MIT
Keywords: lcr,churchofjesuschrist
Author: Isaac Wagner
Author-email: 14634+IsaacsLab42@users.noreply.github.com
Requires-Python: >=3.10,<4.0
Classifier: Development Status :: 5 - Production/Stable
Classifier: Environment :: Console
Classifier: Intended Audience :: Developers
Classifier: Intended Audience :: Religion
Classifier: License :: OSI Approved :: MIT License
Classifier: Natural Language :: English
Classifier: Operating System :: OS Independent
Classifier: Programming Language :: Python :: 3
Classifier: Programming Language :: Python :: 3.10
Classifier: Programming Language :: Python :: 3.11
Classifier: Programming Language :: Python :: 3.12
Classifier: Programming Language :: Python :: 3.13
Classifier: Topic :: Religion
Requires-Dist: fake-useragent (>=1.5.1,<2.0.0)
Requires-Dist: requests (>=2.32.3,<3.0.0)
Project-URL: Bug Tracker, https://github.com/IsaacsLab42/lcr_session/issues
Project-URL: Documentation, https://lcr-session.readthedocs.io/en/stable/
Project-URL: Homepage, https://github.com/IsaacsLab42/lcr_session
Project-URL: Repository, https://github.com/IsaacsLab42/lcr_session
